backupchan_client_config-0.1.2.dist-info/licenses/LICENSE
backupchan_config/__init__.py
backupchan_config/config.py
backupchan_client_config-0.1.2.dist-info/METADATA
backupchan_client_config-0.1.2.dist-info/WHEEL
backupchan_client_config-0.1.2.dist-info/top_level.txt
backupchan_client_config-0.1.2.dist-info/RECORD
