Metadata-Version: 2.4
Name: backupchan-client-config
Version: 0.1.2
Summary: Client-side connection configuration library for Backup-chan.
Author-email: Moltony <koronavirusnyj@gmail.com>
License: BSD-3-Clause
Classifier: Development Status :: 5 - Production/Stable
Classifier: License :: OSI Approved :: BSD License
Classifier: Natural Language :: English
Classifier: Operating System :: OS Independent
Classifier: Programming Language :: Python :: 3 :: Only
Classifier: Topic :: System :: Archiving :: Backup
Classifier: Topic :: Software Development :: Libraries
Classifier: Typing :: Typed
License-File: LICENSE
Requires-Dist: keyring
Requires-Dist: platformdirs
Dynamic: license-file
